{
  "slug": "moonchain",
  "adapter_commit": "a238be25a7a40a6b3809c110a7f152218124adac",
  "extracted_at": "2026-04-26T01:39:03.085Z",
  "adapter_url": "https://github.com/DefiLlama/DefiLlama-Adapters/blob/a238be25a7a40a6b3809c110a7f152218124adac/projects/mxczkevm/index.js",
  "unresolved": false,
  "static_addresses": [
    {
      "chain": "arbitrum",
      "address": "0x0f813f4785b2360009f9ac9bf6121a85f109efc6",
      "context": null,
      "source_line": 12,
      "purpose_hint": "unknown"
    },
    {
      "chain": "arbitrum",
      "address": "0x12e96c2bfea6e835cf8dd38a5834fa61cf723736",
      "context": null,
      "source_line": 12,
      "purpose_hint": "unknown"
    },
    {
      "chain": "arbitrum",
      "address": "0x3160284bc2f4d7f5b170c70a0ee0bc5333c7f39e",
      "context": null,
      "source_line": 10,
      "purpose_hint": "unknown"
    },
    {
      "chain": "arbitrum",
      "address": "0x4c3924e619e2ee83cfd565c1432cb621ca8af7a0",
      "context": null,
      "source_line": 9,
      "purpose_hint": "unknown"
    }
  ],
  "dynamic_resolution": [],
  "imports": [
    "../helper/unwrapLPs"
  ],
  "warnings": []
}
