{
  "slug": "beefy",
  "adapter_commit": "a238be25a7a40a6b3809c110a7f152218124adac",
  "fetched_at": "2026-04-26T13:14:58.056Z",
  "addresses": [
    {
      "chain": "arbitrum",
      "address": "0x0c0846c5d8194bc327669763ac6af9b788edb409",
      "context": null,
      "self_is_safe": false,
      "self_safe": null,
      "self_not_safe_reason": "not_a_safe",
      "owner": "0x9a94784264aaae397441c1e47fa132be4e61bdad",
      "owner_is_safe": false,
      "owner_safe": null,
      "owner_not_safe_reason": "not_a_safe",
      "fetched": {
        "owner": true,
        "self": true,
        "owner_safe": true
      },
      "warnings": []
    },
    {
      "chain": "avax",
      "address": "0x79a8d2cbdcb651013dae6be25a3813ca70f35732",
      "context": null,
      "self_is_safe": false,
      "self_safe": null,
      "self_not_safe_reason": "not_a_safe",
      "owner": null,
      "owner_is_safe": false,
      "owner_safe": null,
      "owner_not_safe_reason": null,
      "fetched": {
        "owner": true,
        "self": true,
        "owner_safe": false
      },
      "warnings": [
        "owner status=0: Free API access is not supported for this chain. Please upgrade your api plan for full chain coverage. https://etherscan.io/apis"
      ]
    },
    {
      "chain": "avax",
      "address": "0x7e74446ee441a8da46f61f9ada7f8368d26e0eea",
      "context": null,
      "self_is_safe": false,
      "self_safe": null,
      "self_not_safe_reason": "not_a_safe",
      "owner": null,
      "owner_is_safe": false,
      "owner_safe": null,
      "owner_not_safe_reason": null,
      "fetched": {
        "owner": true,
        "self": true,
        "owner_safe": false
      },
      "warnings": [
        "owner status=0: Free API access is not supported for this chain. Please upgrade your api plan for full chain coverage. https://etherscan.io/apis"
      ]
    },
    {
      "chain": "avax",
      "address": "0xd1fec8530a8e824f051d80ce17d238e96a75bcb2",
      "context": null,
      "self_is_safe": false,
      "self_safe": null,
      "self_not_safe_reason": "not_a_safe",
      "owner": null,
      "owner_is_safe": false,
      "owner_safe": null,
      "owner_not_safe_reason": null,
      "fetched": {
        "owner": true,
        "self": true,
        "owner_safe": false
      },
      "warnings": [
        "owner status=0: Free API access is not supported for this chain. Please upgrade your api plan for full chain coverage. https://etherscan.io/apis"
      ]
    }
  ],
  "summary": {
    "total": 4,
    "owners_resolved": 1,
    "self_is_safe": 0,
    "owner_is_safe": 0,
    "owner_resolved_not_safe": 1,
    "unique_owner_safes": 0,
    "unique_owners": 1
  }
}
