{
  "slug": "spiko",
  "adapter_commit": "683d36908b5bca5f16752d174c03d928db179af1",
  "extracted_at": "2026-04-28T08:10:47.847Z",
  "adapter_url": "https://github.com/DefiLlama/DefiLlama-Adapters/blob/683d36908b5bca5f16752d174c03d928db179af1/projects/spiko/index.js",
  "unresolved": false,
  "static_addresses": [
    {
      "chain": null,
      "address": "0x021289588cd81dc1ac87ea91e91607eef68303f5",
      "context": null,
      "source_line": 22,
      "purpose_hint": "unknown"
    },
    {
      "chain": null,
      "address": "0x0e389c83bc1d16d86412476f6103027555c03265",
      "context": null,
      "source_line": 25,
      "purpose_hint": "unknown"
    },
    {
      "chain": null,
      "address": "0x3868d4e336d14d38031cf680329d31e4712e11cc",
      "context": null,
      "source_line": 18,
      "purpose_hint": "unknown"
    },
    {
      "chain": null,
      "address": "0x4f33acf823e6eeb697180d553ce0c710124c8d59",
      "context": null,
      "source_line": 17,
      "purpose_hint": "unknown"
    },
    {
      "chain": null,
      "address": "0x903d5990119bc799423e9c25c56518ba7dd19474",
      "context": null,
      "source_line": 10,
      "purpose_hint": "unknown"
    },
    {
      "chain": null,
      "address": "0x970e2adc2fdf53aea6b5fa73ca6dc30eafedfe3d",
      "context": null,
      "source_line": 12,
      "purpose_hint": "unknown"
    },
    {
      "chain": null,
      "address": "0x99f70a0e1786402a6796c6b0aa997ef340a5c6da",
      "context": null,
      "source_line": 11,
      "purpose_hint": "unknown"
    },
    {
      "chain": null,
      "address": "0xa0769f7a8fc65e47de93797b4e21c073c117fc80",
      "context": null,
      "source_line": 9,
      "purpose_hint": "unknown"
    },
    {
      "chain": null,
      "address": "0xa8de1f55aa0e381cb456e1dcc9ff781ea0079068",
      "context": null,
      "source_line": 33,
      "purpose_hint": "unknown"
    },
    {
      "chain": null,
      "address": "0xcbeb19549054cc0a6257a77736fc78c367216ce7",
      "context": null,
      "source_line": 23,
      "purpose_hint": "unknown"
    },
    {
      "chain": null,
      "address": "0xe4880249745eac5f1ed9d8f7df844792d560e750",
      "context": null,
      "source_line": 8,
      "purpose_hint": "unknown"
    },
    {
      "chain": null,
      "address": "0xf695df6c0f3bb45918a7a82e83348fc59517734e",
      "context": null,
      "source_line": 19,
      "purpose_hint": "unknown"
    }
  ],
  "dynamic_resolution": [],
  "imports": [
    "../helper/chain/starknet",
    "../helper/chain/stellar",
    "../helper/http",
    "../helper/unwrapLPs"
  ],
  "warnings": []
}
