{
  "slug": "stakewise-v2",
  "adapter_commit": "683d36908b5bca5f16752d174c03d928db179af1",
  "fetched_at": "2026-04-30T08:59:27.898Z",
  "addresses": [
    {
      "chain": "ethereum",
      "address": "0x09e84205df7c68907e619d07afd90143c5763605",
      "context": null,
      "self_is_safe": false,
      "self_safe": null,
      "self_not_safe_reason": null,
      "owner": null,
      "owner_is_safe": false,
      "owner_safe": null,
      "owner_not_safe_reason": null,
      "fetched": {
        "owner": false,
        "self": true,
        "owner_safe": false
      },
      "warnings": [
        "safe http 429"
      ]
    },
    {
      "chain": "ethereum",
      "address": "0x20bc832ca081b91433ff6c17f85701b6e92486c5",
      "context": "rETH2",
      "self_is_safe": false,
      "self_safe": null,
      "self_not_safe_reason": null,
      "owner": null,
      "owner_is_safe": false,
      "owner_safe": null,
      "owner_not_safe_reason": null,
      "fetched": {
        "owner": false,
        "self": true,
        "owner_safe": false
      },
      "warnings": [
        "safe http 429"
      ]
    },
    {
      "chain": "ethereum",
      "address": "0x3a0008a588772446f6e656133c2d5029cc4fc20e",
      "context": "factory",
      "self_is_safe": false,
      "self_safe": null,
      "self_not_safe_reason": null,
      "owner": null,
      "owner_is_safe": false,
      "owner_safe": null,
      "owner_not_safe_reason": null,
      "fetched": {
        "owner": false,
        "self": true,
        "owner_safe": false
      },
      "warnings": [
        "safe http 429"
      ]
    },
    {
      "chain": "ethereum",
      "address": "0xc02aaa39b223fe8d0a0e5c4f27ead9083c756cc2",
      "context": "WETH",
      "self_is_safe": false,
      "self_safe": null,
      "self_not_safe_reason": "not_a_safe",
      "owner": null,
      "owner_is_safe": false,
      "owner_safe": null,
      "owner_not_safe_reason": null,
      "fetched": {
        "owner": true,
        "self": true,
        "owner_safe": false
      },
      "warnings": []
    },
    {
      "chain": "ethereum",
      "address": "0xeadcba8bf9aca93f627f31fb05470f5a0686ceca",
      "context": "validator",
      "self_is_safe": false,
      "self_safe": null,
      "self_not_safe_reason": null,
      "owner": null,
      "owner_is_safe": false,
      "owner_safe": null,
      "owner_not_safe_reason": null,
      "fetched": {
        "owner": false,
        "self": true,
        "owner_safe": false
      },
      "warnings": [
        "safe http 429"
      ]
    },
    {
      "chain": "ethereum",
      "address": "0xfe2e637202056d30016725477c5da089ab0a043a",
      "context": "sETH2",
      "self_is_safe": false,
      "self_safe": null,
      "self_not_safe_reason": null,
      "owner": null,
      "owner_is_safe": false,
      "owner_safe": null,
      "owner_not_safe_reason": null,
      "fetched": {
        "owner": false,
        "self": true,
        "owner_safe": false
      },
      "warnings": [
        "safe http 429"
      ]
    },
    {
      "chain": "xdai",
      "address": "0x9c58bacc331c9aa871afd802db6379a98e80cedb",
      "context": "GNO",
      "self_is_safe": false,
      "self_safe": null,
      "self_not_safe_reason": null,
      "owner": null,
      "owner_is_safe": false,
      "owner_safe": null,
      "owner_not_safe_reason": null,
      "fetched": {
        "owner": false,
        "self": true,
        "owner_safe": false
      },
      "warnings": [
        "safe http 429"
      ]
    },
    {
      "chain": "xdai",
      "address": "0xa4ef9da5ba71cc0d2e5e877a910a37ec43420445",
      "context": "sGNO",
      "self_is_safe": false,
      "self_safe": null,
      "self_not_safe_reason": null,
      "owner": null,
      "owner_is_safe": false,
      "owner_safe": null,
      "owner_not_safe_reason": null,
      "fetched": {
        "owner": false,
        "self": true,
        "owner_safe": false
      },
      "warnings": [
        "safe http 429"
      ]
    }
  ],
  "summary": {
    "total": 8,
    "owners_resolved": 0,
    "self_is_safe": 0,
    "owner_is_safe": 0,
    "owner_resolved_not_safe": 0,
    "unique_owner_safes": 0,
    "unique_owners": 0
  }
}
