{
  "slug": "sablier-flow",
  "extracted_at": "2026-04-30T03:27:26.857Z",
  "audits": [
    {
      "firm": null,
      "date": "2026-03-27",
      "url": "https://github.com/sablier-labs/audits/blob/main/bob/v1.0/20260327_cyfrin_fv.pdf",
      "source": "github-aggregator",
      "raw_name": "20260327_cyfrin_fv"
    },
    {
      "firm": null,
      "date": "2026-03-25",
      "url": "https://github.com/sablier-labs/audits/blob/main/bob/v1.0/20260325_cyfrin.pdf",
      "source": "github-aggregator",
      "raw_name": "20260325_cyfrin"
    },
    {
      "firm": null,
      "date": "2025-09-29",
      "url": "https://github.com/sablier-labs/audits/blob/main/staking/v1.0/20250929_chaindefenders.pdf",
      "source": "github-aggregator",
      "raw_name": "20250929_chaindefenders"
    },
    {
      "firm": null,
      "date": "2024-06-28",
      "url": "https://github.com/sablier-labs/audits/blob/main/lockup/v1.2/20240628_egis.pdf",
      "source": "github-aggregator",
      "raw_name": "20240628_egis"
    },
    {
      "firm": null,
      "date": "2023-11-30",
      "url": "https://github.com/sablier-labs/audits/blob/main/lockup/v1.1/20231130_turing.pdf",
      "source": "github-aggregator",
      "raw_name": "20231130_turing"
    },
    {
      "firm": null,
      "date": "2023-07-09",
      "url": "https://github.com/sablier-labs/audits/blob/main/lockup/v1.0/20230709_iaro_periphery.pdf",
      "source": "github-aggregator",
      "raw_name": "20230709_iaro_periphery"
    },
    {
      "firm": null,
      "date": "2023-06-13",
      "url": "https://github.com/sablier-labs/audits/blob/main/lockup/v1.0/20230613_iaro_core.pdf",
      "source": "github-aggregator",
      "raw_name": "20230613_iaro_core"
    },
    {
      "firm": null,
      "date": "2023-04-24",
      "url": "https://github.com/sablier-labs/audits/blob/main/lockup/v1.0/20230424_rahul.pdf",
      "source": "github-aggregator",
      "raw_name": "20230424_rahul"
    },
    {
      "firm": null,
      "date": "2023-04-04",
      "url": "https://github.com/sablier-labs/audits/blob/main/lockup/v1.0/20230404_iaro_core.pdf",
      "source": "github-aggregator",
      "raw_name": "20230404_iaro_core"
    },
    {
      "firm": null,
      "date": "2023-04-03",
      "url": "https://github.com/sablier-labs/audits/blob/main/lockup/v1.0/20230403_hydn.pdf",
      "source": "github-aggregator",
      "raw_name": "20230403_hydn"
    },
    {
      "firm": null,
      "date": "2023-03-31",
      "url": "https://github.com/sablier-labs/audits/blob/main/lockup/v1.0/20230331_hake.pdf",
      "source": "github-aggregator",
      "raw_name": "20230331_hake"
    },
    {
      "firm": null,
      "url": "https://github.com/sablier-labs/audits",
      "date": null,
      "source": "defillama"
    },
    {
      "firm": "Cantina",
      "date": "2026-03-18",
      "url": "https://github.com/sablier-labs/audits/blob/main/airdrops/v3.0/20260318_cantina.pdf",
      "source": "github-aggregator",
      "raw_name": "20260318_cantina"
    },
    {
      "firm": "Cantina",
      "date": "2026-03-18",
      "url": "https://github.com/sablier-labs/audits/blob/main/evm-utils/v2.0/20260318_cantina.pdf",
      "source": "github-aggregator",
      "raw_name": "20260318_cantina"
    },
    {
      "firm": "Cantina",
      "date": "2026-03-18",
      "url": "https://github.com/sablier-labs/audits/blob/main/flow/v3.0/20260318_cantina.pdf",
      "source": "github-aggregator",
      "raw_name": "20260318_cantina"
    },
    {
      "firm": "Cantina",
      "date": "2026-03-18",
      "url": "https://github.com/sablier-labs/audits/blob/main/lockup/v4.0/20260318_cantina.pdf",
      "source": "github-aggregator",
      "raw_name": "20260318_cantina"
    },
    {
      "firm": "Cantina",
      "date": "2025-10-14",
      "url": "https://github.com/sablier-labs/audits/blob/main/staking/v1.0/20251014_cantina.pdf",
      "source": "github-aggregator",
      "raw_name": "20251014_cantina"
    },
    {
      "firm": "Cantina",
      "date": "2025-08-25",
      "url": "https://github.com/sablier-labs/audits/blob/main/solsab/v1.0/20250825_cantina.pdf",
      "source": "github-aggregator",
      "raw_name": "20250825_cantina"
    },
    {
      "firm": "Cantina",
      "date": "2025-07-28",
      "url": "https://github.com/sablier-labs/audits/blob/main/airdrops/v2.0/20250728_cantina.pdf",
      "source": "github-aggregator",
      "raw_name": "20250728_cantina"
    },
    {
      "firm": "Cantina",
      "date": "2025-07-28",
      "url": "https://github.com/sablier-labs/audits/blob/main/evm-utils/v1.0/20250728_cantina.pdf",
      "source": "github-aggregator",
      "raw_name": "20250728_cantina"
    },
    {
      "firm": "Cantina",
      "date": "2025-07-28",
      "url": "https://github.com/sablier-labs/audits/blob/main/flow/v2.0/20250728_cantina.pdf",
      "source": "github-aggregator",
      "raw_name": "20250728_cantina"
    },
    {
      "firm": "Cantina",
      "date": "2025-07-28",
      "url": "https://github.com/sablier-labs/audits/blob/main/lockup/v3.0/20250728_cantina.pdf",
      "source": "github-aggregator",
      "raw_name": "20250728_cantina"
    },
    {
      "firm": "Cantina",
      "date": "2025-04-05",
      "url": "https://github.com/sablier-labs/audits/blob/main/airdrops/v2.0/20250405_cantina.pdf",
      "source": "github-aggregator",
      "raw_name": "20250405_cantina"
    },
    {
      "firm": "Cantina",
      "date": "2025-04-05",
      "url": "https://github.com/sablier-labs/audits/blob/main/flow/v2.0/20250405_cantina.pdf",
      "source": "github-aggregator",
      "raw_name": "20250405_cantina"
    },
    {
      "firm": "Cantina",
      "date": "2025-04-05",
      "url": "https://github.com/sablier-labs/audits/blob/main/lockup/v3.0/20250405_cantina.pdf",
      "source": "github-aggregator",
      "raw_name": "20250405_cantina"
    },
    {
      "firm": "Cantina",
      "date": "2025-01-12",
      "url": "https://github.com/sablier-labs/audits/blob/main/airdrops/v1.3/20250112_cantina.pdf",
      "source": "github-aggregator",
      "raw_name": "20250112_cantina"
    },
    {
      "firm": "Cantina",
      "date": "2025-01-12",
      "url": "https://github.com/sablier-labs/audits/blob/main/flow/v1.1/20250112_cantina.pdf",
      "source": "github-aggregator",
      "raw_name": "20250112_cantina"
    },
    {
      "firm": "Cantina",
      "date": "2025-01-12",
      "url": "https://github.com/sablier-labs/audits/blob/main/lockup/v2.0/20250112_cantina.pdf",
      "source": "github-aggregator",
      "raw_name": "20250112_cantina"
    },
    {
      "firm": "Cantina",
      "date": "2024-10-20",
      "url": "https://github.com/sablier-labs/audits/blob/main/flow/v1.0/20241020_cantina.pdf",
      "source": "github-aggregator",
      "raw_name": "20241020_cantina"
    },
    {
      "firm": "Cantina",
      "date": "2024-07-03",
      "url": "https://github.com/sablier-labs/audits/blob/main/lockup/v1.2/20240703_cantina.pdf",
      "source": "github-aggregator",
      "raw_name": "20240703_cantina"
    },
    {
      "firm": "Cantina",
      "date": "2024-06-13",
      "url": "https://github.com/sablier-labs/audits/blob/main/lockup/v1.2/20240613_cantina.pdf",
      "source": "github-aggregator",
      "raw_name": "20240613_cantina"
    },
    {
      "firm": "Cantina",
      "date": "2023-12-21",
      "url": "https://github.com/sablier-labs/audits/blob/main/lockup/v1.1/20231221_cantina.pdf",
      "source": "github-aggregator",
      "raw_name": "20231221_cantina"
    },
    {
      "firm": "Cantina",
      "date": "2023-12-15",
      "url": "https://github.com/sablier-labs/audits/blob/main/lockup/v1.1/20231215_cantina.pdf",
      "source": "github-aggregator",
      "raw_name": "20231215_cantina"
    },
    {
      "firm": "Cantina",
      "date": "2023-09-06",
      "url": "https://github.com/sablier-labs/audits/blob/main/lockup/v1.1/20230906_cantina.pdf",
      "source": "github-aggregator",
      "raw_name": "20230906_cantina"
    },
    {
      "firm": "Cantina",
      "date": "2023-06-08",
      "url": "https://github.com/sablier-labs/audits/blob/main/lockup/v1.0/20230608_cantina.pdf",
      "source": "github-aggregator",
      "raw_name": "20230608_cantina"
    },
    {
      "firm": "Quantstamp",
      "date": "2019-11-25",
      "url": "https://github.com/sablier-labs/audits/blob/main/legacy/20191125_quantstamp.pdf",
      "source": "github-aggregator",
      "raw_name": "20191125_quantstamp"
    }
  ]
}
