{
  "slug": "unidex-perp",
  "adapter_commit": "a238be25a7a40a6b3809c110a7f152218124adac",
  "extracted_at": "2026-04-26T01:39:03.085Z",
  "adapter_url": "https://github.com/DefiLlama/DefiLlama-Adapters/blob/a238be25a7a40a6b3809c110a7f152218124adac/projects/unidex/index.js",
  "unresolved": false,
  "static_addresses": [
    {
      "chain": "arbitrum",
      "address": "0x031d35296154279dc1984dcd93e392b1f946737b",
      "context": "cap",
      "source_line": 49,
      "purpose_hint": "unknown"
    },
    {
      "chain": "arbitrum",
      "address": "0x09e122453a079bc2be621769ae7799e53da0054e",
      "context": "usdcPool",
      "source_line": 22,
      "purpose_hint": "pool"
    },
    {
      "chain": "arbitrum",
      "address": "0x0ae38f7e10a43b5b2fb064b42a2f4514cba909ef",
      "context": "tvl",
      "source_line": 53,
      "purpose_hint": "unknown"
    },
    {
      "chain": "arbitrum",
      "address": "0x13ff1ab07540b1681173003e361d046530506c11",
      "context": "gnsPool",
      "source_line": 33,
      "purpose_hint": "pool"
    },
    {
      "chain": "arbitrum",
      "address": "0x18c11fd286c5ec11c3b683caa813b77f5163a122",
      "context": "gns",
      "source_line": 48,
      "purpose_hint": "unknown"
    },
    {
      "chain": "arbitrum",
      "address": "0x266b30394da3d99a846dd30a2f7c50bb523c5de1",
      "context": "mimPool",
      "source_line": 27,
      "purpose_hint": "pool"
    },
    {
      "chain": "arbitrum",
      "address": "0x2f2a2543b76a4166549f7aab2e75bef0aefc5b0f",
      "context": "WBTC",
      "source_line": 40,
      "purpose_hint": "token"
    },
    {
      "chain": "arbitrum",
      "address": "0x5372af9b4e9d4b9c016574dad0f2406dfe023d5f",
      "context": "unshethPool",
      "source_line": 35,
      "purpose_hint": "pool"
    },
    {
      "chain": "arbitrum",
      "address": "0x53c6c525a635ef56bce43d4523d90aace551d81b",
      "context": "wstethPool",
      "source_line": 32,
      "purpose_hint": "pool"
    },
    {
      "chain": "arbitrum",
      "address": "0x5979d7b546e38e414f7e9822514be443a4800529",
      "context": "WSTETH",
      "source_line": 45,
      "purpose_hint": "token"
    },
    {
      "chain": "arbitrum",
      "address": "0x7638db20715c5ac09f52be1e3a4dbb220680bdfd",
      "context": "gdaiPool",
      "source_line": 28,
      "purpose_hint": "pool"
    },
    {
      "chain": "arbitrum",
      "address": "0x912ce59144191c1204e64559fe8253a0e49e6548",
      "context": "ARB",
      "source_line": 41,
      "purpose_hint": "unknown"
    },
    {
      "chain": "arbitrum",
      "address": "0x914172b52262e867d8f2959d884e0ea73795b2c6",
      "context": "ramPool",
      "source_line": 29,
      "purpose_hint": "pool"
    },
    {
      "chain": "arbitrum",
      "address": "0x99ddb3e66a592579b9d46a47824042f62d690a9e",
      "context": "capPool",
      "source_line": 34,
      "purpose_hint": "pool"
    },
    {
      "chain": "arbitrum",
      "address": "0x9f6b9e253de52c5fd6c65283ff472b15520a7070",
      "context": "usdtPool",
      "source_line": 24,
      "purpose_hint": "pool"
    },
    {
      "chain": "arbitrum",
      "address": "0xaaa6c1e32c55a7bfa8066a6fae9b42650f262418",
      "context": "ram",
      "source_line": 44,
      "purpose_hint": "unknown"
    },
    {
      "chain": "arbitrum",
      "address": "0xb764729c6bebd6e60e151f2c46afce7d6ff513fd",
      "context": "daiPool",
      "source_line": 23,
      "purpose_hint": "pool"
    },
    {
      "chain": "arbitrum",
      "address": "0xd85e038593d7a098614721eae955ec2022b9b91b",
      "context": "tvl",
      "source_line": 53,
      "purpose_hint": "unknown"
    },
    {
      "chain": "arbitrum",
      "address": "0xdaa78e776d3788f9fbabdac02aa6de45f7bc50c6",
      "context": "gmxPool",
      "source_line": 31,
      "purpose_hint": "pool"
    },
    {
      "chain": "arbitrum",
      "address": "0xdaf7d157f5c6e0f1d7917ca02a7c185cef81e6d0",
      "context": "ethPool",
      "source_line": 21,
      "purpose_hint": "pool"
    },
    {
      "chain": "arbitrum",
      "address": "0xe736742eb62f271c48f4a26168fd8f356aee68db",
      "context": "wbtcPool",
      "source_line": 25,
      "purpose_hint": "pool"
    },
    {
      "chain": "arbitrum",
      "address": "0xefd0b28810dc3cdd88763f40dcc44462bb85cf32",
      "context": "maiPool",
      "source_line": 30,
      "purpose_hint": "pool"
    },
    {
      "chain": "arbitrum",
      "address": "0xf1cb521c753e41906073ebed30fe34bcb00845f8",
      "context": "arbPool",
      "source_line": 26,
      "purpose_hint": "pool"
    },
    {
      "chain": "arbitrum",
      "address": "0xfc5a1a6eb076a2c7ad06ed22c90d7e710e35ad0a",
      "context": "GMX",
      "source_line": 46,
      "purpose_hint": "unknown"
    },
    {
      "chain": "arbitrum",
      "address": "0xfd086bc7cd5c481dcc9c85ebe478a1c0b69fcbb9",
      "context": "USDT",
      "source_line": 39,
      "purpose_hint": "token"
    },
    {
      "chain": "arbitrum",
      "address": "0xfea7a6a0b346362bf88a9e4a88416b77a57d6c2a",
      "context": "MIM",
      "source_line": 42,
      "purpose_hint": "unknown"
    },
    {
      "chain": "arbitrum",
      "address": "0xff970a61a04b1ca14834a43f5de4533ebddb5cc8",
      "context": "USDC",
      "source_line": 37,
      "purpose_hint": "token"
    },
    {
      "chain": "base",
      "address": "0x9ba3db52bc401f4ef8ba23e56268c3ade0290837",
      "context": "ethpool",
      "source_line": 70,
      "purpose_hint": "pool"
    },
    {
      "chain": "boba",
      "address": "0x9673b0e0f07e4a6da712f6847ae93c3f157dd509",
      "context": "ethpool",
      "source_line": 60,
      "purpose_hint": "pool"
    },
    {
      "chain": "bsc",
      "address": "0xa8d4bd632f394ced42bd439bc34f09198072e519",
      "context": "busdPool",
      "source_line": 126,
      "purpose_hint": "pool"
    },
    {
      "chain": "bsc",
      "address": "0xe9e7cea3dedca5984780bafc599bd69add087d56",
      "context": "BUSD",
      "source_line": 128,
      "purpose_hint": "unknown"
    },
    {
      "chain": "era",
      "address": "0x3355df6d4c9c3035724fd0e3914de96a5a83aaf4",
      "context": "USDC",
      "source_line": 14,
      "purpose_hint": "token"
    },
    {
      "chain": "era",
      "address": "0xa41a6a4a04e711b53a82e594ceb525e89206627a",
      "context": "usdcPool",
      "source_line": 115,
      "purpose_hint": "pool"
    },
    {
      "chain": "evmos",
      "address": "0x21708707f03a19c3a4ea5e1a132b5cf96b86f294",
      "context": "stevmosPool",
      "source_line": 80,
      "purpose_hint": "pool"
    },
    {
      "chain": "evmos",
      "address": "0x2c68d1d6ab986ff4640b51e1f14c716a076e44c4",
      "context": "STEVMOS",
      "source_line": 82,
      "purpose_hint": "unknown"
    },
    {
      "chain": "fantom",
      "address": "0x04068da6c83afcfa0e13ba15a6696662335d5b75",
      "context": "USDC",
      "source_line": 11,
      "purpose_hint": "token"
    },
    {
      "chain": "fantom",
      "address": "0x7a494c755911ce06444c47248108439a06ac028c",
      "context": "usdcPool",
      "source_line": 8,
      "purpose_hint": "pool"
    },
    {
      "chain": "fantom",
      "address": "0x8d11ec38a3eb5e956b052f67da8bdc9bef8abf3e",
      "context": "DAI",
      "source_line": 12,
      "purpose_hint": "token"
    },
    {
      "chain": "fantom",
      "address": "0xbec7d4561037e657830f78b87e780aee1d09fc7b",
      "context": "ftmPool",
      "source_line": 7,
      "purpose_hint": "pool"
    },
    {
      "chain": "fantom",
      "address": "0xc451df1b05828519c014cb967ef1a614bd41834d",
      "context": "daiPool",
      "source_line": 9,
      "purpose_hint": "pool"
    },
    {
      "chain": "metis",
      "address": "0x420000000000000000000000000000000000000a",
      "context": "WETH",
      "source_line": 94,
      "purpose_hint": "token"
    },
    {
      "chain": "metis",
      "address": "0x9ba3db52bc401f4ef8ba23e56268c3ade0290837",
      "context": "metisPool",
      "source_line": 91,
      "purpose_hint": "pool"
    },
    {
      "chain": "metis",
      "address": "0xb3d7d548da38dac2876da57842a3cbaaf9a3bd96",
      "context": "wethPool",
      "source_line": 92,
      "purpose_hint": "pool"
    },
    {
      "chain": "optimism",
      "address": "0x68a4cf26705b3ceab49d1c99de98f3db28ee767e",
      "context": "ethPool",
      "source_line": 104,
      "purpose_hint": "pool"
    },
    {
      "chain": "optimism",
      "address": "0xcddf71750e596b4c38785affec3bd4c9bff43f6f",
      "context": "daiPool",
      "source_line": 103,
      "purpose_hint": "pool"
    },
    {
      "chain": "optimism",
      "address": "0xda10009cbd5d07dd0cecc66161fc93d7c9000da1",
      "context": "DAI",
      "source_line": 14,
      "purpose_hint": "token"
    }
  ],
  "dynamic_resolution": [],
  "imports": [
    "../helper/coreAssets.json",
    "../helper/unwrapLPs"
  ],
  "warnings": []
}
