{
  "slug": "unsheth",
  "adapter_commit": "a238be25a7a40a6b3809c110a7f152218124adac",
  "extracted_at": "2026-04-26T01:39:03.085Z",
  "adapter_url": "https://github.com/DefiLlama/DefiLlama-Adapters/blob/a238be25a7a40a6b3809c110a7f152218124adac/projects/unsheth/index.js",
  "unresolved": false,
  "static_addresses": [
    {
      "chain": "ethereum",
      "address": "0x51a80238b5738725128d3a3e06ab41c1d4c05c74",
      "context": "LSDVAULT_CONTRACT_V2",
      "source_line": 11,
      "purpose_hint": "vault"
    },
    {
      "chain": "ethereum",
      "address": "0xe76ffee8722c21b390eebe71b67d95602f58237f",
      "context": "LSDVAULT_CONTRACT_V1",
      "source_line": 18,
      "purpose_hint": "vault"
    }
  ],
  "dynamic_resolution": [],
  "imports": [
    "../helper/cache/getLogs",
    "../helper/unwrapLPs"
  ],
  "warnings": []
}
