{
  "slug": "arcadia-v1",
  "extracted_at": "2026-04-29T21:51:34.557Z",
  "audits": [
    {
      "firm": null,
      "url": "https://github.com/NethermindEth/PublicAuditReports/blob/main/NM0072-FINAL_ARCADIA.pdf",
      "date": null,
      "source": "defillama"
    },
    {
      "firm": null,
      "url": "https://solidity.finance/audits/ArcadiaFinance",
      "date": null,
      "source": "defillama"
    },
    {
      "firm": "Sherlock",
      "url": "https://github.com/sherlock-protocol/sherlock-reports/blob/main/audits/2024.04.25%20-%20Final%20-%20Arcadia%20-%20Aerodrome%20integrations%20Audit%20Report.pdf",
      "date": "2024-04-25",
      "source": "auditor-repo",
      "raw_name": "Arcadia - Aerodrome integrations"
    },
    {
      "firm": "Sherlock",
      "url": "https://github.com/sherlock-protocol/sherlock-reports/blob/main/audits/2024.02.16%20-%20Final%20-%20Arcadia%20Audit%20Report.pdf",
      "date": "2024-02-16",
      "source": "auditor-repo",
      "raw_name": "Arcadia"
    }
  ]
}
