{
  "slug": "sperax-demeter",
  "adapter_commit": "683d36908b5bca5f16752d174c03d928db179af1",
  "fetched_at": "2026-05-06T04:11:00.308Z",
  "etherscan_v": "v2",
  "addresses": [
    {
      "chain": "arbitrum",
      "address": "0xc4fb09e0cd212367642974f6ba81d8e23780a659",
      "context": "tvl",
      "etherscan": {
        "fetched": true,
        "verified": false,
        "contract_name": null,
        "compiler": null,
        "optimization": false,
        "is_proxy": true,
        "implementation": "0xbb14ed437c66f45f2018135089f0725059e80d56"
      },
      "sourcify": {
        "fetched": true,
        "status": "false"
      },
      "warnings": []
    }
  ],
  "summary": {
    "total": 1,
    "verified_etherscan": 0,
    "verified_sourcify": 0,
    "proxies": 1,
    "skipped_unsupported_chain": 0,
    "skipped_etherscan": 0
  }
}
