{
  "slug": "revert-compoundor",
  "adapter_commit": "a238be25a7a40a6b3809c110a7f152218124adac",
  "fetched_at": "2026-04-26T05:25:55.605Z",
  "etherscan_v": "v2",
  "addresses": [
    {
      "chain": "arbitrum",
      "address": "0x5411894842e610c4d0f6ed4c232da689400f94a1",
      "context": null,
      "etherscan": {
        "fetched": true,
        "verified": true,
        "contract_name": "Compoundor",
        "compiler": "v0.7.6+commit.7338295f",
        "optimization": true,
        "is_proxy": false,
        "implementation": null
      },
      "sourcify": {
        "fetched": true,
        "status": "perfect"
      },
      "warnings": []
    },
    {
      "chain": "bsc",
      "address": "0x98ec492942090364ac0736ef1a741ae6c92ec790",
      "context": null,
      "etherscan": {
        "fetched": true,
        "verified": true,
        "contract_name": "Compoundor",
        "compiler": "v0.7.6+commit.7338295f",
        "optimization": true,
        "is_proxy": false,
        "implementation": null
      },
      "sourcify": {
        "fetched": true,
        "status": "perfect"
      },
      "warnings": []
    },
    {
      "chain": "ethereum",
      "address": "0x5411894842e610c4d0f6ed4c232da689400f94a1",
      "context": null,
      "etherscan": {
        "fetched": true,
        "verified": true,
        "contract_name": "Compoundor",
        "compiler": "v0.7.6+commit.7338295f",
        "optimization": true,
        "is_proxy": false,
        "implementation": null
      },
      "sourcify": {
        "fetched": true,
        "status": "perfect"
      },
      "warnings": []
    },
    {
      "chain": "optimism",
      "address": "0x5411894842e610c4d0f6ed4c232da689400f94a1",
      "context": null,
      "etherscan": {
        "fetched": true,
        "verified": true,
        "contract_name": "Compoundor",
        "compiler": "v0.7.6+commit.7338295f",
        "optimization": true,
        "is_proxy": false,
        "implementation": null
      },
      "sourcify": {
        "fetched": true,
        "status": "perfect"
      },
      "warnings": []
    },
    {
      "chain": "polygon",
      "address": "0x5411894842e610c4d0f6ed4c232da689400f94a1",
      "context": null,
      "etherscan": {
        "fetched": true,
        "verified": true,
        "contract_name": "Compoundor",
        "compiler": "v0.7.6+commit.7338295f",
        "optimization": true,
        "is_proxy": false,
        "implementation": null
      },
      "sourcify": {
        "fetched": true,
        "status": "false"
      },
      "warnings": []
    }
  ],
  "summary": {
    "total": 5,
    "verified_etherscan": 5,
    "verified_sourcify": 4,
    "proxies": 0,
    "skipped_unsupported_chain": 0,
    "skipped_etherscan": 0
  }
}
