{
  "slug": "hashport",
  "adapter_commit": "683d36908b5bca5f16752d174c03d928db179af1",
  "extracted_at": "2026-04-28T08:10:47.847Z",
  "adapter_url": "https://github.com/DefiLlama/DefiLlama-Adapters/blob/683d36908b5bca5f16752d174c03d928db179af1/projects/hashport/index.js",
  "unresolved": false,
  "static_addresses": [
    {
      "chain": null,
      "address": "0x0f3414b61b902513e04e76ca4d1a7b003d09f54b",
      "context": "base",
      "source_line": 16,
      "purpose_hint": "unknown"
    },
    {
      "chain": null,
      "address": "0x367e59b559283c8506207d75b0c5d8c66c4cd4b7",
      "context": "ethereum",
      "source_line": 8,
      "purpose_hint": "unknown"
    },
    {
      "chain": null,
      "address": "0x36daafd7c305677905a643cf1a0c74a281c6413c",
      "context": "cronos",
      "source_line": 17,
      "purpose_hint": "unknown"
    },
    {
      "chain": null,
      "address": "0x3b32202a662353dcb4dbb983adbdf2ab49181506",
      "context": "aurora",
      "source_line": 18,
      "purpose_hint": "unknown"
    },
    {
      "chain": null,
      "address": "0x475b21ade54b9494d8201e0330ca7994081f4e0f",
      "context": "fantom",
      "source_line": 14,
      "purpose_hint": "unknown"
    },
    {
      "chain": null,
      "address": "0x617d29b4bae43b3aa3d63b7f61177600036d2f6b",
      "context": "moonbeam",
      "source_line": 15,
      "purpose_hint": "unknown"
    },
    {
      "chain": null,
      "address": "0x6da4e99b62b8d910e1688e34121cd8d50b7c0c3e",
      "context": "optimism",
      "source_line": 12,
      "purpose_hint": "unknown"
    },
    {
      "chain": null,
      "address": "0x9021926be887355b76e60f4148ebb6b3f1ffafcc",
      "context": "bsc",
      "source_line": 10,
      "purpose_hint": "unknown"
    },
    {
      "chain": null,
      "address": "0x984bb007b41a865bd8a9db9ca919000fbab5893a",
      "context": "arbitrum",
      "source_line": 13,
      "purpose_hint": "unknown"
    },
    {
      "chain": null,
      "address": "0xd8df34a071179fe8cef910ae0b43cde49d611b49",
      "context": "avax",
      "source_line": 11,
      "purpose_hint": "unknown"
    },
    {
      "chain": null,
      "address": "0xf4c0153a8bdb3dfe8d135ce3be0d45e14e5ce53d",
      "context": "polygon",
      "source_line": 9,
      "purpose_hint": "unknown"
    }
  ],
  "dynamic_resolution": [],
  "imports": [
    "../helper/http",
    "../helper/unwrapLPs",
    "@defillama/sdk"
  ],
  "warnings": []
}
