{
  "slug": "aquabank",
  "adapter_commit": "683d36908b5bca5f16752d174c03d928db179af1",
  "extracted_at": "2026-04-28T08:10:47.847Z",
  "adapter_url": "https://github.com/DefiLlama/DefiLlama-Adapters/blob/683d36908b5bca5f16752d174c03d928db179af1/projects/aquabank/index.js",
  "unresolved": false,
  "static_addresses": [
    {
      "chain": null,
      "address": "0x3c594084dc7ab1864ac69dfd01ab77e8f65b83b7",
      "context": "bUSDt",
      "source_line": 4,
      "purpose_hint": "unknown"
    },
    {
      "chain": null,
      "address": "0x61e8f77ed693d3edecbcc2dd9c55c1d987c47775",
      "context": null,
      "source_line": 17,
      "purpose_hint": "unknown"
    },
    {
      "chain": null,
      "address": "0x7d336b49879a173626e51bff780686d88b8081ec",
      "context": null,
      "source_line": 14,
      "purpose_hint": "unknown"
    },
    {
      "chain": null,
      "address": "0xb06de2e9a339d201661045b7d845de3d20373b4f",
      "context": null,
      "source_line": 15,
      "purpose_hint": "unknown"
    },
    {
      "chain": null,
      "address": "0xccb7de5b7788de551e3b85b50e4834d5b7e3f27c",
      "context": null,
      "source_line": 16,
      "purpose_hint": "unknown"
    },
    {
      "chain": "avax",
      "address": "0x190d94613a09ad7931fcd17cd6a8f9b6b47ad414",
      "context": "tvl",
      "source_line": 22,
      "purpose_hint": "unknown"
    },
    {
      "chain": "avax",
      "address": "0xa446938b0204aa4055cdfed68ddf0e0d1bab3e9e",
      "context": "tvl",
      "source_line": 22,
      "purpose_hint": "unknown"
    },
    {
      "chain": "avax",
      "address": "0xb715808a78f6041e46d61cb123c9b4a27056ae9c",
      "context": "tvl",
      "source_line": 22,
      "purpose_hint": "unknown"
    },
    {
      "chain": "avax",
      "address": "0xd8fcda6ec4bdc547c0827b8804e89acd817d56ef",
      "context": "tvl",
      "source_line": 22,
      "purpose_hint": "unknown"
    }
  ],
  "dynamic_resolution": [],
  "imports": [
    "@defillama/sdk"
  ],
  "warnings": []
}
