{
  "slug": "toupee.tech",
  "adapter_commit": "683d36908b5bca5f16752d174c03d928db179af1",
  "fetched_at": "2026-04-29T08:11:19.315Z",
  "etherscan_v": null,
  "addresses": [
    {
      "chain": "base",
      "address": "0x4200000000000000000000000000000000000006",
      "context": "WETH",
      "etherscan": {
        "fetched": true,
        "verified": true,
        "contract_name": "WETH9",
        "compiler": "v0.5.17+commit.d19bba13",
        "optimization": true,
        "is_proxy": false,
        "implementation": null
      },
      "sourcify": {
        "fetched": true,
        "status": "false"
      },
      "warnings": []
    },
    {
      "chain": "base",
      "address": "0x58dd173f30ecffdfebcd242c71241fb2f179e9b9",
      "context": "staking",
      "etherscan": {
        "fetched": true,
        "verified": true,
        "contract_name": "TOKEN",
        "compiler": "v0.8.19+commit.7dd6d404",
        "optimization": true,
        "is_proxy": false,
        "implementation": null
      },
      "sourcify": {
        "fetched": true,
        "status": "perfect"
      },
      "warnings": []
    },
    {
      "chain": "base",
      "address": "0x60c08737877a5262bdb1c1cac8fb90b5e5b11515",
      "context": "staking",
      "etherscan": {
        "fetched": true,
        "verified": true,
        "contract_name": "VTOKEN",
        "compiler": "v0.8.19+commit.7dd6d404",
        "optimization": true,
        "is_proxy": false,
        "implementation": null
      },
      "sourcify": {
        "fetched": true,
        "status": "perfect"
      },
      "warnings": []
    }
  ],
  "summary": {
    "total": 3,
    "verified_etherscan": 3,
    "verified_sourcify": 2,
    "proxies": 0,
    "skipped_unsupported_chain": 0,
    "skipped_etherscan": 0
  }
}
