{
  "slug": "cove-boosties",
  "adapter_commit": "683d36908b5bca5f16752d174c03d928db179af1",
  "fetched_at": "2026-04-30T08:07:37.465Z",
  "addresses": [
    {
      "chain": "ethereum",
      "address": "0x0bc529c00c6401aef6d220be8c6ea1667f6ad93e",
      "context": "YFI",
      "self_is_safe": false,
      "self_safe": null,
      "self_not_safe_reason": "not_a_safe",
      "owner": null,
      "owner_is_safe": false,
      "owner_safe": null,
      "owner_not_safe_reason": null,
      "fetched": {
        "owner": true,
        "self": true,
        "owner_safe": false
      },
      "warnings": []
    },
    {
      "chain": "ethereum",
      "address": "0x842b22eb2a1c1c54344eddbe6959f787c2d15844",
      "context": "factory",
      "self_is_safe": false,
      "self_safe": null,
      "self_not_safe_reason": "not_a_safe",
      "owner": null,
      "owner_is_safe": false,
      "owner_safe": null,
      "owner_not_safe_reason": null,
      "fetched": {
        "owner": true,
        "self": true,
        "owner_safe": false
      },
      "warnings": []
    }
  ],
  "summary": {
    "total": 2,
    "owners_resolved": 0,
    "self_is_safe": 0,
    "owner_is_safe": 0,
    "owner_resolved_not_safe": 0,
    "unique_owner_safes": 0,
    "unique_owners": 0
  }
}
