{
  "slug": "lista-cdp",
  "adapter_commit": "683d36908b5bca5f16752d174c03d928db179af1",
  "extracted_at": "2026-04-28T08:10:47.847Z",
  "adapter_url": "https://github.com/DefiLlama/DefiLlama-Adapters/blob/683d36908b5bca5f16752d174c03d928db179af1/projects/helio-money/index.js",
  "unresolved": false,
  "static_addresses": [
    {
      "chain": null,
      "address": "0x1cf9c6d475cdca67942d41b0a34bd9cb9d336c4d",
      "context": null,
      "source_line": 10,
      "purpose_hint": "unknown"
    },
    {
      "chain": null,
      "address": "0x4b2d67bf25245783fc4c33a48962775437f9159c",
      "context": null,
      "source_line": 7,
      "purpose_hint": "unknown"
    },
    {
      "chain": null,
      "address": "0x9eb77a54a33069a319d91f493e6b1c9066fb38f7",
      "context": null,
      "source_line": 11,
      "purpose_hint": "unknown"
    },
    {
      "chain": null,
      "address": "0xc23d348f9cc86ddb059ec798e87e7f76fbc077c1",
      "context": null,
      "source_line": 8,
      "purpose_hint": "unknown"
    },
    {
      "chain": null,
      "address": "0xe8f4644637f127aff11f9492f41269eb5e8b8dd2",
      "context": null,
      "source_line": 5,
      "purpose_hint": "unknown"
    },
    {
      "chain": null,
      "address": "0xf6ab5cfdb46357f37b0190b793fb199d62dcf504",
      "context": null,
      "source_line": 9,
      "purpose_hint": "unknown"
    },
    {
      "chain": null,
      "address": "0xff5ed1e64aca62c822b178ffa5c36b40c112eb00",
      "context": null,
      "source_line": 6,
      "purpose_hint": "unknown"
    },
    {
      "chain": "bsc",
      "address": "0xd0c380d31db43cd291e2bbe2da2fd6dc877b87b3",
      "context": null,
      "source_line": 39,
      "purpose_hint": "unknown"
    },
    {
      "chain": "bsc",
      "address": "0xfceb31a79f71ac9cbdcf853519c1b12d379edc46",
      "context": null,
      "source_line": 39,
      "purpose_hint": "unknown"
    }
  ],
  "dynamic_resolution": [],
  "imports": [
    "../helper/cache",
    "../helper/staking"
  ],
  "warnings": []
}
