{
  "slug": "conduit-bridge",
  "adapter_commit": "a238be25a7a40a6b3809c110a7f152218124adac",
  "fetched_at": "2026-04-26T14:00:08.131Z",
  "addresses": [
    {
      "chain": "ethereum",
      "address": "0x14ea6add7fa61001bd2e38100bfdf2cd710e44d9",
      "context": null,
      "self_is_safe": false,
      "self_safe": null,
      "self_not_safe_reason": "not_a_safe",
      "owner": null,
      "owner_is_safe": false,
      "owner_safe": null,
      "owner_not_safe_reason": null,
      "fetched": {
        "owner": true,
        "self": true,
        "owner_safe": false
      },
      "warnings": []
    },
    {
      "chain": "ethereum",
      "address": "0xbaedb5b6da67f96b4125f17dd92f618696494bd3",
      "context": null,
      "self_is_safe": false,
      "self_safe": null,
      "self_not_safe_reason": "not_a_safe",
      "owner": null,
      "owner_is_safe": false,
      "owner_safe": null,
      "owner_not_safe_reason": null,
      "fetched": {
        "owner": true,
        "self": true,
        "owner_safe": false
      },
      "warnings": []
    }
  ],
  "summary": {
    "total": 2,
    "owners_resolved": 0,
    "self_is_safe": 0,
    "owner_is_safe": 0,
    "owner_resolved_not_safe": 0,
    "unique_owner_safes": 0,
    "unique_owners": 0
  }
}
