{
  "slug": "dexfinance-bsc",
  "adapter_commit": "a238be25a7a40a6b3809c110a7f152218124adac",
  "fetched_at": "2026-04-26T14:11:09.530Z",
  "addresses": [
    {
      "chain": "bsc",
      "address": "0x4c7371a351a465c38dc129e4d084b9b8aef14041",
      "context": "REWARD_POOL",
      "self_is_safe": false,
      "self_safe": null,
      "self_not_safe_reason": "not_a_safe",
      "owner": null,
      "owner_is_safe": false,
      "owner_safe": null,
      "owner_not_safe_reason": null,
      "fetched": {
        "owner": true,
        "self": true,
        "owner_safe": false
      },
      "warnings": [
        "owner status=0: Free API access is not supported for this chain. Please upgrade your api plan for full chain coverage. https://etherscan.io/apis"
      ]
    },
    {
      "chain": "bsc",
      "address": "0x60ebfd605cb25c7796f729c78a4453acecb1ce03",
      "context": "ETF_INDEX_POOL",
      "self_is_safe": false,
      "self_safe": null,
      "self_not_safe_reason": "not_a_safe",
      "owner": null,
      "owner_is_safe": false,
      "owner_safe": null,
      "owner_not_safe_reason": null,
      "fetched": {
        "owner": true,
        "self": true,
        "owner_safe": false
      },
      "warnings": [
        "owner status=0: Free API access is not supported for this chain. Please upgrade your api plan for full chain coverage. https://etherscan.io/apis"
      ]
    },
    {
      "chain": "bsc",
      "address": "0xbb4cdb9cbd36b01bd1cbaebf2de08d9173bc095c",
      "context": "WBNB",
      "self_is_safe": false,
      "self_safe": null,
      "self_not_safe_reason": "not_a_safe",
      "owner": null,
      "owner_is_safe": false,
      "owner_safe": null,
      "owner_not_safe_reason": null,
      "fetched": {
        "owner": true,
        "self": true,
        "owner_safe": false
      },
      "warnings": [
        "owner status=0: Free API access is not supported for this chain. Please upgrade your api plan for full chain coverage. https://etherscan.io/apis"
      ]
    },
    {
      "chain": "bsc",
      "address": "0xcc180bfa5d2c3ac191758b721c9bbbb263b3fd1c",
      "context": "FARM",
      "self_is_safe": false,
      "self_safe": null,
      "self_not_safe_reason": "not_a_safe",
      "owner": null,
      "owner_is_safe": false,
      "owner_safe": null,
      "owner_not_safe_reason": null,
      "fetched": {
        "owner": true,
        "self": true,
        "owner_safe": false
      },
      "warnings": [
        "owner status=0: Free API access is not supported for this chain. Please upgrade your api plan for full chain coverage. https://etherscan.io/apis"
      ]
    },
    {
      "chain": "bsc",
      "address": "0xd69db827939e26511068aa2bf742e7463b292190",
      "context": "REGULATION_STAKING_POOL",
      "self_is_safe": false,
      "self_safe": null,
      "self_not_safe_reason": "not_a_safe",
      "owner": null,
      "owner_is_safe": false,
      "owner_safe": null,
      "owner_not_safe_reason": null,
      "fetched": {
        "owner": true,
        "self": true,
        "owner_safe": false
      },
      "warnings": [
        "owner status=0: Free API access is not supported for this chain. Please upgrade your api plan for full chain coverage. https://etherscan.io/apis"
      ]
    }
  ],
  "summary": {
    "total": 5,
    "owners_resolved": 0,
    "self_is_safe": 0,
    "owner_is_safe": 0,
    "owner_resolved_not_safe": 0,
    "unique_owner_safes": 0,
    "unique_owners": 0
  }
}
