{
  "slug": "open-ticketing-ecosystem",
  "adapter_commit": "683d36908b5bca5f16752d174c03d928db179af1",
  "fetched_at": "2026-05-06T03:50:59.512Z",
  "etherscan_v": "v2",
  "addresses": [
    {
      "chain": "ethereum",
      "address": "0x686e8500b6be8812eb198aabbbfa14c95c03fc88",
      "context": "stakingContractPolygon",
      "etherscan": {
        "fetched": true,
        "verified": true,
        "contract_name": "GovernanceLockedRevenueDistributionToken",
        "compiler": "v0.8.7+commit.e28d00a7",
        "optimization": true,
        "is_proxy": false,
        "implementation": null
      },
      "sourcify": {
        "fetched": true,
        "status": "perfect"
      },
      "warnings": []
    },
    {
      "chain": "ethereum",
      "address": "0xc28eb2250d1ae32c7e74cfb6d6b86afc9beb6509",
      "context": "openTokenEthereum",
      "etherscan": {
        "fetched": true,
        "verified": true,
        "contract_name": "OPNToken",
        "compiler": "v0.8.7+commit.e28d00a7",
        "optimization": true,
        "is_proxy": false,
        "implementation": null
      },
      "sourcify": {
        "fetched": true,
        "status": "perfect"
      },
      "warnings": []
    },
    {
      "chain": "polygon",
      "address": "0x686e8500b6be8812eb198aabbbfa14c95c03fc88",
      "context": "stakingContractPolygon",
      "etherscan": {
        "fetched": true,
        "verified": true,
        "contract_name": "GovernanceLockedRevenueDistributionToken",
        "compiler": "v0.8.7+commit.e28d00a7",
        "optimization": true,
        "is_proxy": false,
        "implementation": null
      },
      "sourcify": {
        "fetched": true,
        "status": "false"
      },
      "warnings": []
    },
    {
      "chain": "polygon",
      "address": "0x7844f79fc841e4f92d974c417031c76f8578c2d5",
      "context": "openTokenAddressPolygon",
      "etherscan": {
        "fetched": true,
        "verified": true,
        "contract_name": "UChildERC20Proxy",
        "compiler": "v0.6.6+commit.6c089d02",
        "optimization": false,
        "is_proxy": true,
        "implementation": "0xc856c55a7d20350b0bfe98a100dffdee0929e7cb"
      },
      "sourcify": {
        "fetched": true,
        "status": "perfect"
      },
      "warnings": []
    }
  ],
  "summary": {
    "total": 4,
    "verified_etherscan": 4,
    "verified_sourcify": 3,
    "proxies": 1,
    "skipped_unsupported_chain": 0,
    "skipped_etherscan": 0
  }
}
