{
  "slug": "rho-protocol",
  "adapter_commit": "a238be25a7a40a6b3809c110a7f152218124adac",
  "extracted_at": "2026-04-26T01:39:03.085Z",
  "adapter_url": "https://github.com/DefiLlama/DefiLlama-Adapters/blob/a238be25a7a40a6b3809c110a7f152218124adac/projects/rho-protocol/index.js",
  "unresolved": false,
  "static_addresses": [
    {
      "chain": "arbitrum",
      "address": "0xb5855e692465b6c1b5172fcaf59ac67f20621a4d",
      "context": "tvl",
      "source_line": 11,
      "purpose_hint": "unknown"
    }
  ],
  "dynamic_resolution": [],
  "imports": [
    "./abi/collateral",
    "./abi/contract-provider",
    "./abi/market"
  ],
  "warnings": []
}
